html_creator/__init__.py
html_creator/test.py
html_creator-1.1.dist-info/LICENSE
html_creator-1.1.dist-info/METADATA
html_creator-1.1.dist-info/WHEEL
html_creator-1.1.dist-info/top_level.txt
html_creator-1.1.dist-info/RECORD
