Metadata-Version: 2.1
Name: html-creator
Version: 1.1
Summary: Dynamic HTML code generation
Home-page: https://github.com/iTecAI/html-creator
Author: iTecX
Author-email: matteovh@gmail.com
License: UNKNOWN
Platform: UNKNOWN
Classifier: Programming Language :: Python :: 3
Classifier: License :: OSI Approved :: MIT License
Classifier: Operating System :: OS Independent
